django_suit_rq-1.0.1.dist-info/DESCRIPTION.rst
django_suit_rq-1.0.1.dist-info/METADATA
django_suit_rq-1.0.1.dist-info/metadata.json
django_suit_rq-1.0.1.dist-info/RECORD
django_suit_rq-1.0.1.dist-info/top_level.txt
django_suit_rq-1.0.1.dist-info/WHEEL
suit_rq/__init__.py
suit_rq/apps.py
suit_rq/migrations/0001_initial.py
suit_rq/migrations/__init__.py
suit_rq/templates/django_rq/clear_queue.html
suit_rq/templates/django_rq/confirm_action.html
suit_rq/templates/django_rq/delete_job.html
suit_rq/templates/django_rq/job_detail.html
suit_rq/templates/django_rq/jobs.html
suit_rq/templates/django_rq/stats.html
